Metadata-Version: 2.1
Name: chunksv
Version: 0.1.0
Summary: Python module for processing csv files in chunks.
Home-page: https://github.com/bengetch/chunksv
Author: bengetch
Author-email: bengetch@gmail.com
License: MIT
Platform: UNKNOWN
Requires-Python: >=3.8
License-File: LICENSE
